yta_multimedia_utils/__init__.py
yta_multimedia_utils/dimensions.py
yta_multimedia_utils/resize.py
yta_multimedia_utils-0.0.3.dist-info/LICENSE
yta_multimedia_utils-0.0.3.dist-info/METADATA
yta_multimedia_utils-0.0.3.dist-info/WHEEL
yta_multimedia_utils-0.0.3.dist-info/RECORD
