Metadata-Version: 2.3
Name: yta-multimedia-utils
Version: 0.0.3
Summary: 
Author: danialcala94
Author-email: danielalcalavalera@gmail.com
Requires-Python: ==3.9
Classifier: Programming Language :: Python :: 3
Classifier: Programming Language :: Python :: 3.9
Requires-Dist: opencv-python (>=4.11.0.86,<5.0.0.0)
Requires-Dist: yta_file (>=0.0.1,<1.0.0)
Requires-Dist: yta_validation (>=0.0.1,<1.0.0)
